zas_rep_tools/__init__.py
zas_rep_tools/cli/.DS_Store
zas_rep_tools/cli/__init__.py
zas_rep_tools/cli/__init__.pyc
zas_rep_tools/cli/main.py
zas_rep_tools/cli/main.pyc
zas_rep_tools/data/.DS_Store
zas_rep_tools/data/__init__.py
zas_rep_tools/data/__init__.pyc
zas_rep_tools/data/tests_data/.DS_Store
zas_rep_tools/data/tests_data/__init__.py
zas_rep_tools/data/tests_data/__init__.pyc
zas_rep_tools/data/tests_data/Corpora/.DS_Store
zas_rep_tools/data/tests_data/Corpora/__init__.py
zas_rep_tools/data/tests_data/Corpora/__init__.pyc
zas_rep_tools/data/tests_data/Corpora/BloggerCorpus/.DS_Store
zas_rep_tools/data/tests_data/Corpora/BloggerCorpus/__init__.py
zas_rep_tools/data/tests_data/Corpora/BloggerCorpus/__init__.pyc
zas_rep_tools/data/tests_data/Corpora/BloggerCorpus/csv.zip
zas_rep_tools/data/tests_data/Corpora/BloggerCorpus/json.zip
zas_rep_tools/data/tests_data/Corpora/BloggerCorpus/sqlite.zip
zas_rep_tools/data/tests_data/Corpora/BloggerCorpus/txt.zip
zas_rep_tools/data/tests_data/Corpora/BloggerCorpus/xml.zip
zas_rep_tools/data/tests_data/Corpora/BloggerCorpus/csv/__init__.py
zas_rep_tools/data/tests_data/Corpora/BloggerCorpus/csv/__init__.pyc
zas_rep_tools/data/tests_data/Corpora/BloggerCorpus/csv/HighRepetativSubSet/__init__.py
zas_rep_tools/data/tests_data/Corpora/BloggerCorpus/csv/HighRepetativSubSet/__init__.pyc
zas_rep_tools/data/tests_data/Corpora/BloggerCorpus/csv/HighRepetativSubSet/blogger_corpus_0.csv
zas_rep_tools/data/tests_data/Corpora/BloggerCorpus/csv/HighRepetativSubSet/blogger_corpus_1.csv
zas_rep_tools/data/tests_data/Corpora/BloggerCorpus/csv/SmallFakeSubset/__init__.py
zas_rep_tools/data/tests_data/Corpora/BloggerCorpus/csv/SmallFakeSubset/__init__.pyc
zas_rep_tools/data/tests_data/Corpora/BloggerCorpus/csv/SmallFakeSubset/blogger_corpus_0.csv
zas_rep_tools/data/tests_data/Corpora/BloggerCorpus/csv/SmallFakeSubset/blogger_corpus_1.csv
zas_rep_tools/data/tests_data/Corpora/BloggerCorpus/csv/SmallSubset/__init__.py
zas_rep_tools-0.2.dist-info/LICENSE
zas_rep_tools-0.2.dist-info/METADATA
zas_rep_tools-0.2.dist-info/WHEEL
zas_rep_tools-0.2.dist-info/entry_points.txt
zas_rep_tools-0.2.dist-info/top_level.txt
zas_rep_tools-0.2.dist-info/RECORD
