Metadata-Version: 2.1
Name: zas-rep-tools
Version: 0.2
Summary: This Tool-set helps to make the repetition search in text much comfortable and faster.
Home-page: https://github.com/savin-berlin/zas-rep-tools
Author: Egor Savin
Author-email: science@savin.berlin
License: MIT
Platform: UNKNOWN
Classifier: Development Status :: 1 - Planning
Classifier: Intended Audience :: Science/Research
Classifier: License :: OSI Approved :: MIT License
Classifier: Programming Language :: Python :: 2.7
Classifier: Operating System :: MacOS :: MacOS X
Classifier: Operating System :: Microsoft :: Windows :: Windows 10
Classifier: Operating System :: Unix
Classifier: Programming Language :: Java
Classifier: Programming Language :: Python :: 3
Classifier: Topic :: Scientific/Engineering :: Information Analysis
Classifier: Topic :: Text Processing :: Linguistic
Requires-Dist: sure
Requires-Dist: nose
Requires-Dist: rednose
Requires-Dist: blessings
Requires-Dist: testfixtures
Requires-Dist: click
Requires-Dist: regex
Requires-Dist: cached-property
Requires-Dist: raven
Requires-Dist: email
Requires-Dist: tweepy
Requires-Dist: nltk
Requires-Dist: langid
Requires-Dist: lxml
Requires-Dist: logutils
Requires-Dist: pyhashxx
Requires-Dist: colored-traceback
Requires-Dist: colorama
Requires-Dist: unicodecsv
Requires-Dist: psutil
Requires-Dist: execnet
Requires-Dist: validate-email
Requires-Dist: console-menu
Requires-Dist: python-twitter
Requires-Dist: twitter
Requires-Dist: enlighten
Requires-Dist: emoji
Requires-Dist: textblob
Requires-Dist: textblob-de
Requires-Dist: textblob-fr
Requires-Dist: kitchen
Requires-Dist: uniseg
Requires-Dist: pystemmer
Requires-Dist: ZODB
